caipyra/__init__.py
caipyra/estatisticas.py
caipyra/java.py
caipyra/scala.py
caipyra/this.py
caipyra-0.4.dist-info/LICENSE
caipyra-0.4.dist-info/METADATA
caipyra-0.4.dist-info/WHEEL
caipyra-0.4.dist-info/top_level.txt
caipyra-0.4.dist-info/RECORD
