Metadata-Version: 1.0
Name: caipyra
Version: 0.4
Summary: Caipyra 2016 poem
Home-page: http://github.com/jtemporal/caipyra
Author: Jessica Temporal
Author-email: jessicatemporal@gmail.com
License: MIT
Platform: UNKNOWN
